vnd_arxml_shortname/__init__.py
vnd_arxml_shortname/arxml_shortname.py
vnd_arxml_shortname-0.0.5.dist-info/METADATA
vnd_arxml_shortname-0.0.5.dist-info/WHEEL
vnd_arxml_shortname-0.0.5.dist-info/top_level.txt
vnd_arxml_shortname-0.0.5.dist-info/RECORD
